awsinsights/__init__.py
awsinsights/__main__.py
awsinsights/awsinsights.py
awsinsights-1.0.4.dist-info/LICENSE
awsinsights-1.0.4.dist-info/METADATA
awsinsights-1.0.4.dist-info/WHEEL
awsinsights-1.0.4.dist-info/entry_points.txt
awsinsights-1.0.4.dist-info/top_level.txt
awsinsights-1.0.4.dist-info/RECORD
