Metadata-Version: 2.1
Name: awsinsights
Version: 1.0.4
Summary: Get, sort and analyse AWS CloudWatch logs from multiple log groups using AWS CloudWatch Insights service
Home-page: https://github.com/DamZiobro/awsinsights
Author: Damian Ziobro
Author-email: damian@xmementoit.com
License: MIT
Platform: UNKNOWN
Classifier: License :: OSI Approved :: MIT License
Classifier: Programming Language :: Python :: 3
Requires-Python: >=3.3
Requires-Dist: boto3 (>=1.13.5)
